tests/__init__.py
tests/config/__init__.py
tests/config/api_configuration.py
tests/resources/__init__.py
tests/resources/greeting_resoource.py
zpy/__init__.py
zpy/api/__init__.py
zpy/api/errors.py
zpy/api/exceptions.py
zpy/api/hooks.py
zpy/api/middleware.py
zpy/api/models.py
zpy/api/reponse.py
zpy/api/repository.py
zpy/api/resource.py
zpy/api/service.py
zpy/api/stages.py
zpy/api/validator.py
zpy/cloud/__init__.py
zpy/cloud/aws/__init__.py
zpy/cloud/aws/firehose.py
zpy/cloud/aws/s3.py
zpy/cloud/aws/sqs.py
zpy/cloud/aws/ssm.py
zpy/cloud/aws/ssm_paramater_store.py
zpy/constants/__init__.py
zpy/custom/__init__.py
zpy/custom/models.py
zpy/custom/plugins.py
zpy/db/__init__.py
zpy/db/oracle.py
zpy/db/transaction.py
zpy/db/utils.py
zpy/logger/__init__.py
zpy/utils/Encryptor.py
zpy/utils/GZip.py
zpy/utils/__init__.py
zpy/utils/collections.py
zpy/utils/funcs.py
zpy_flask_msc-0.0.1.dist-info/LICENSE
zpy_flask_msc-0.0.1.dist-info/METADATA
zpy_flask_msc-0.0.1.dist-info/WHEEL
zpy_flask_msc-0.0.1.dist-info/top_level.txt
zpy_flask_msc-0.0.1.dist-info/RECORD
