Metadata-Version: 2.1
Name: zpy-flask-msc
Version: 0.0.1
Summary: Helper layer for apis development with Python and Flask
Home-page: https://github.com/NoeCruzMW
Author: Noé Cruz | linkedin.com/in/zurckz/
Author-email: zurckz.services@gmail.com
License: UNKNOWN
Platform: UNKNOWN
Classifier: Programming Language :: Python :: 3
Classifier: License :: OSI Approved :: MIT License
Classifier: Operating System :: OS Independent
Requires-Python: >=3.6
License-File: LICENSE
Requires-Dist: pycryptodome
Requires-Dist: pycryptodomex
Requires-Dist: Flask
Requires-Dist: flask-rest-api
Requires-Dist: Flask-RESTful
Requires-Dist: marshmallow
Requires-Dist: python-dotenv
Requires-Dist: flask-cors
Requires-Dist: cx-Oracle
Requires-Dist: marshmallow-objects
